dash_signature/Signature.py
dash_signature/Test.py
dash_signature/__init__.py
dash_signature/_imports_.py
dash_signature/dash_signature.min.js
dash_signature/dash_signature.min.js.LICENSE.txt
dash_signature/dash_signature.min.js.map
dash_signature/metadata.json
dash_signature/package-info.json
dash_signature-0.1.10.dist-info/LICENSE
dash_signature-0.1.10.dist-info/METADATA
dash_signature-0.1.10.dist-info/WHEEL
dash_signature-0.1.10.dist-info/entry_points.txt
dash_signature-0.1.10.dist-info/RECORD
