Metadata-Version: 2.3
Name: Dash-Signature
Version: 0.1.10
Summary: Signature element for Dash sites in Python
License: MIT
Author: Coulton Fraser
Author-email: cjrfraser@gmail.com
Requires-Python: >=3.11,<4.0
Classifier: License :: OSI Approved :: MIT License
Classifier: Programming Language :: Python :: 3
Classifier: Programming Language :: Python :: 3.11
Classifier: Programming Language :: Python :: 3.12
Classifier: Programming Language :: Python :: 3.13
Requires-Dist: dash (>=2.17.0)
Requires-Dist: twine (>=5.1.1,<6.0.0)
